fastapi_plugins/__init__.py
fastapi_plugins/_redis.py
fastapi_plugins/control.py
fastapi_plugins/logger.py
fastapi_plugins/memcached.py
fastapi_plugins/middleware.py
fastapi_plugins/plugin.py
fastapi_plugins/scheduler.py
fastapi_plugins/settings.py
fastapi_plugins/utils.py
fastapi_plugins/version.py
fastapi_plugins-0.14.0.dist-info/licenses/LICENSE
fastapi_plugins-0.14.0.dist-info/METADATA
fastapi_plugins-0.14.0.dist-info/WHEEL
fastapi_plugins-0.14.0.dist-info/top_level.txt
fastapi_plugins-0.14.0.dist-info/RECORD
