Metadata-Version: 2.4
Name: fastapi-plugins
Version: 0.14.0
Summary: Plugins for FastAPI framework
Author-email: madkote <madkote@bluewin.ch>
License: Copyright 2025, madkote, MIT
Project-URL: homepage, https://github.com/madkote/fastapi-plugins
Project-URL: repository, https://github.com/madkote/fastapi-plugins
Keywords: fastapi,plugin,asyncio,async,redis,aioredis,json,aiojobs,scheduler,starlette,aiomcache,memcached
Classifier: Programming Language :: Python
Classifier: Programming Language :: Python :: 3
Classifier: Operating System :: OS Independent
Classifier: Topic :: Utilities
Classifier: Topic :: Software Development :: Libraries
Classifier: Topic :: Software Development :: Libraries :: Python Modules
Classifier: Topic :: System :: Logging
Classifier: Framework :: AsyncIO
Classifier: Operating System :: OS Independent
Classifier: Intended Audience :: Developers
Requires-Python: <4,>=3.6
License-File: LICENSE
Requires-Dist: fastapi<1,>=0.100
Requires-Dist: pydantic<3,>=2
Requires-Dist: pydantic-settings<3,>=2
Requires-Dist: aiojobs<2,>=1
Requires-Dist: aiomcache>=0.7.0
Requires-Dist: orjson<4,>=3
Requires-Dist: python-json-logger>=2
Requires-Dist: redis[hiredis]<5,>=4.3.0
Requires-Dist: tenacity>=8
Provides-Extra: dev
Requires-Dist: aiofiles; extra == "dev"
Requires-Dist: aioresponses; extra == "dev"
Requires-Dist: bandit; extra == "dev"
Requires-Dist: build; extra == "dev"
Requires-Dist: docker-compose; extra == "dev"
Requires-Dist: fakeredis[lua]>=1.8.0; extra == "dev"
Requires-Dist: fastapi[all]; extra == "dev"
Requires-Dist: flake8; extra == "dev"
Requires-Dist: Flake8-pyproject; extra == "dev"
Requires-Dist: isort; extra == "dev"
Requires-Dist: pdm; extra == "dev"
Requires-Dist: pytest; extra == "dev"
Requires-Dist: pytest-asyncio<1.0,>=0.1; extra == "dev"
Requires-Dist: pytest-cov; extra == "dev"
Requires-Dist: PyYAML!=5.4.0,!=5.4.1,<6,>=5.3.1; extra == "dev"
Requires-Dist: setuptools; extra == "dev"
Requires-Dist: tox; extra == "dev"
Requires-Dist: twine; extra == "dev"
Requires-Dist: wheel; extra == "dev"
Dynamic: license-file
